aria_tools/__init__.py
aria_tools/__main__.py
aria_tools/actions.py
aria_tools/constants.py
aria_tools/deno_utils.py
aria_tools/register_tools.py
aria_tools/server_utils.py
aria_tools/html_templates/__init__.py
aria_tools/tools/__init__.py
aria_tools/tools/best_pubmed_query.py
aria_tools/tools/diagrammer.py
aria_tools/tools/html_pager.py
aria_tools/tools/isa_parser.py
aria_tools/tools/protocol_reviewer.py
aria_tools/tools/protocol_updater.py
aria_tools/tools/protocol_writer.py
aria_tools/tools/pubmed_hitter.py
aria_tools/tools/pubmed_querier.py
aria_tools/tools/study_suggester.py
aria_tools/utils/__init__.py
aria_tools/utils/agents.py
aria_tools/utils/config.py
aria_tools/utils/io.py
aria_tools/utils/models.py
aria_tools-0.0.1.dist-info/licenses/LICENSE
aria_tools-0.0.1.dist-info/METADATA
aria_tools-0.0.1.dist-info/WHEEL
aria_tools-0.0.1.dist-info/top_level.txt
aria_tools-0.0.1.dist-info/RECORD
