Metadata-Version: 2.4
Name: aria-tools
Version: 0.0.1
Summary: Aria tools for use by Aria Agents through Hypha.
License-Expression: MIT
Requires-Python: >=3.11
License-File: LICENSE
Requires-Dist: schema-agents<0.2.0,>=0.1.0
Requires-Dist: hypha<0.21.0,>=0.20.0
Requires-Dist: hypha-rpc<0.21.0,>=0.20.0
Requires-Dist: biopython>=1.8
Requires-Dist: dotenv>=0.9
Requires-Dist: pydantic<3.0,>=2.0
Dynamic: license-file
